LICENSE.txt
MANIFEST.in
README
setup.py
PyTestGame.egg-info/PKG-INFO
PyTestGame.egg-info/SOURCES.txt
PyTestGame.egg-info/dependency_links.txt
PyTestGame.egg-info/top_level.txt
wargame/__init__.py
wargame/abstractgameunit.py
wargame/attackoftheorcs.py
wargame/gameuniterror.py
wargame/gameutils.py
wargame/hut.py
wargame/knight.py
wargame/orcrider.py