Metadata-Version: 1.0
Name: PyTestGame
Version: 2.0.0
Summary: test pkg ignore
Home-page: https://testpypi.python.org/pypi/PyTestGame/
Author: PythonTest
Author-email: wangshilei@loongson.cn
License: LICENSE.txt
Platform: UNKNOWN
